{"startdate": "20210613", "fullstartdate": "202106132200", "enddate": "20210614", "url": "/th?id=OHR.SpiritMaligne_DE-DE0626334314_1920x1080.jpg&rf=LaDigue_1920x1080.jpg&pid=hp", "urlbase": "/th?id=OHR.SpiritMaligne_DE-DE0626334314", "copyright": "Spirit Island im Maligne Lake, Jasper-Nationalpark, Alberta, Kanada (\u00a9 Jeff Penner/EyeEm/Getty Images)", "copyrightlink": "https://www.bing.com/search?q=Insel+Spirit+Island+Kanada&form=hpcapt&filters=HpDate%3a%2220210613_2200%22", "title": "Ein Paradies f\u00fcr Fotografen", "quiz": "/search?q=Bing+homepage+quiz&filters=WQOskey:%22HPQuiz_20210613_SpiritMaligne%22&FORM=HPQUIZ", "wp": true, "hsh": "91c9fd4dc9ba21a10793febe5b33d5b4", "drk": 1, "top": 1, "bot": 1, "hs": []}